LICENSE.rst
MANIFEST.in
README.rst
setup.py
codemirror/__init__.py
codemirror/fields.py
codemirror/utils.py
codemirror/widgets.py
django_codemirror_widget.egg-info/PKG-INFO
django_codemirror_widget.egg-info/SOURCES.txt
django_codemirror_widget.egg-info/dependency_links.txt
django_codemirror_widget.egg-info/top_level.txt
django_codemirror_widget.egg-info/zip-safe